CheeseType/__init__.py
CheeseType/default.py
CheeseType/network.py
CheeseType-0.0.3.dist-info/LICENSE
CheeseType-0.0.3.dist-info/METADATA
CheeseType-0.0.3.dist-info/WHEEL
CheeseType-0.0.3.dist-info/top_level.txt
CheeseType-0.0.3.dist-info/RECORD
