Metadata-Version: 2.1
Name: CheeseType
Version: 0.0.3
Summary: 存放了一些常用自定义类型的库。
Home-page: https://github.com/CheeseUnknown/CheeseType
Author: Cheese Unknown
Author-email: cheese@cheese.ren
License: MIT
Keywords: type
Classifier: License :: OSI Approved :: MIT License
Classifier: Programming Language :: Python :: 3.11
Requires-Python: >=3.11
License-File: LICENSE
